and_no_refresh/circuit.v
/* Generated by Yosys 0.13 (git sha1 8b1eafc3a, clang 10.0.0-4ubuntu1 -fPIC -Os) */

module and_no_refresh(clk, rstn, a0, a1, b0, b1, r, x0, x1);
  input a0;
  input a1;
  input b0;
  input b1;
  input clk;
  wire cross_a0_b1;
  wire cross_b0_a1;
  wire inner_a0_b0;
  wire inner_a1_b1;
  wire integ_x0;
  wire integ_x1;
  input r;
  wire refresh_a0_b0_r;
  wire refresh_a1_b1_r;
  reg reshare_x0;
  reg reshare_x1;
  reg reshare_x2;
  reg reshare_x3;
  input rstn;
  output x0;
  output x1;
  always @(posedge clk, negedge rstn)
    if (!rstn) reshare_x0 <= 1'h0;
    else reshare_x0 <= refresh_a0_b0_r;
  always @(posedge clk, negedge rstn)
    if (!rstn) reshare_x1 <= 1'h0;
    else reshare_x1 <= cross_a0_b1;
  always @(posedge clk, negedge rstn)
    if (!rstn) reshare_x2 <= 1'h0;
    else reshare_x2 <= cross_b0_a1;
  always @(posedge clk, negedge rstn)
    if (!rstn) reshare_x3 <= 1'h0;
    else reshare_x3 <= refresh_a1_b1_r;
  assign inner_a0_b0 = a0 & b0;
  assign cross_a0_b1 = a0 & b1;
  assign inner_a1_b1 = a1 & b1;
  assign cross_b0_a1 = a1 & b0;
  assign refresh_a0_b0_r = inner_a0_b0 ^ r;
  assign refresh_a1_b1_r = inner_a1_b1 ^ r;
  assign x0 = reshare_x0 ^ reshare_x1;
  assign x1 = reshare_x2 ^ reshare_x3;
  assign integ_x0 = x0;
  assign integ_x1 = x1;
endmodule

and_no_refresh/tb_and_no_refresh.sv
`timescale 1ns/1ps
`default_nettype none
module tb_and_no_refresh;
   logic clk, rstn;
   logic a0, a1;
   logic b0, b1;
   logic r;
   logic x0, x1;

   logic [3:0] idx;

   initial begin
      $dumpfile("trace.vcd");
      $dumpvars(0, tb_and_no_refresh);
      {clk, rstn, a0, a1, b0, b1, r} = 7'h0;
      #15 rstn = 1'b1;
      for(idx = 0; idx <= 4'he; idx++) begin
	 {a0, a1, b0, b1} = idx;
	 #5;
      end
      #100 $finish();
   end

   always #5 clk++;
   and_no_refresh uut (clk, rstn, a0, a1, b0, b1, r, x0, x1);
endmodule // tb_and_no_refresh
`default_nettype wire

and_no_refresh/trace.vcd
$date
	Sun Sep  4 21:13:03 2022
$end
$version
	Icarus Verilog
$end
$timescale
	1ps
$end
$scope module tb_and_no_refresh $end
$var wire 1 ! x1 $end
$var wire 1 " x0 $end
$var reg 1 # a0 $end
$var reg 1 $ a1 $end
$var reg 1 % b0 $end
$var reg 1 & b1 $end
$var reg 1 ' clk $end
$var reg 4 ( idx [3:0] $end
$var reg 1 ) r $end
$var reg 1 * rstn $end
$scope module uut $end
$var wire 1 # a0 $end
$var wire 1 $ a1 $end
$var wire 1 % b0 $end
$var wire 1 & b1 $end
$var wire 1 ' clk $end
$var wire 1 + cross_a0_b1 $end
$var wire 1 , cross_b0_a1 $end
$var wire 1 - inner_a0_b0 $end
$var wire 1 . inner_a1_b1 $end
$var wire 1 / integ_x0 $end
$var wire 1 0 integ_x1 $end
$var wire 1 ) r $end
$var wire 1 1 refresh_a0_b0_r $end
$var wire 1 2 refresh_a1_b1_r $end
$var wire 1 * rstn $end
$var wire 1 " x0 $end
$var wire 1 ! x1 $end
$var reg 1 3 reshare_x0 $end
$var reg 1 4 reshare_x1 $end
$var reg 1 5 reshare_x2 $end
$var reg 1 6 reshare_x3 $end
$upscope $end
$upscope $end
$enddefinitions $end
#0
$dumpvars
06
05
04
03
02
01
00
0/
0.
0-
0,
0+
0*
0)
bx (
0'
0&
0%
0$
0#
0"
0!
$end
#5000
1'
#10000
0'
#15000
1'
b0 (
1*
#20000
0'
1&
b1 (
#25000
1'
1%
0&
b10 (
#30000
0'
1&
b11 (
#35000
1'
1$
0%
0&
b100 (
#40000
12
1.
0'
1&
b101 (
#45000
16
15
02
1,
0.
1'
1%
0&
b110 (
#50000
12
1.
0'
1&
b111 (
#55000
10
1!
05
02
0,
0.
1'
1#
0$
0%
0&
b1000 (
#60000
1+
0'
1&
b1001 (
#65000
00
0!
06
11
1-
0+
1'
1%
0&
b1010 (
#70000
1+
0'
1&
b1011 (
#75000
1/
1"
13
01
0-
0+
1'
1$
0%
0&
b1100 (
#80000
12
1+
1.
0'
1&
b1101 (
#85000
0/
0"
16
15
03
11
02
1-
1,
0+
0.
1'
1%
0&
b1110 (
#90000
0'
b1111 (
#95000
1/
1"
10
1!
13
06
1'
